spaceman3D/__init__.py
spaceman3D/Draw/__init__.py
spaceman3D/Draw/astronomical_objects.py
spaceman3D/Draw/draw.py
spaceman3D/Orbit/__init__.py
spaceman3D/Orbit/orbit.py
spaceman3D/Orbit/satellites.py
spaceman3D/Orbit/tle.py
spaceman3D/Tests/__init__.py
spaceman3D/Tests/test.py
Spaceman3D-0.1.0.dist-info/LICENSE
Spaceman3D-0.1.0.dist-info/METADATA
Spaceman3D-0.1.0.dist-info/WHEEL
Spaceman3D-0.1.0.dist-info/top_level.txt
Spaceman3D-0.1.0.dist-info/RECORD
