Metadata-Version: 2.1
Name: Spaceman3D
Version: 0.1.0
Summary: Spaceman3D is a package that parses and creates 3D plots of the satellite's orbits using Two-Line Element (TLE) Data.
Home-page: https://github.com/Jaseibert/Spaceman
Author: Jeremy A. Seibert
Author-email: Jaseibert2@eagles.usi.edu
License: UNKNOWN
Platform: UNKNOWN
Classifier: Programming Language :: Python :: 3
Classifier: Programming Language :: Python :: 3.6
Classifier: Programming Language :: Python :: 3.7
Classifier: License :: OSI Approved :: MIT License
Classifier: Operating System :: OS Independent
